MANIFEST.in
README.rst
setup.py
zeroless/__init__.py
zeroless/zeroless.py
zeroless.egg-info/PKG-INFO
zeroless.egg-info/SOURCES.txt
zeroless.egg-info/dependency_links.txt
zeroless.egg-info/not-zip-safe
zeroless.egg-info/requires.txt
zeroless.egg-info/top_level.txt
zeroless_helpers/__init__.py
zeroless_helpers/version.py