Metadata-Version: 1.1
Name: zeroless
Version: 1.0.0
Summary: ZeroMQ for Pythonistas™
Home-page: https://github.com/zmqless/python-zeroless
Author: Lucas Lira Gomes
Author-email: x8lucas8x@gmail.com
License: LGPLv2+
Keywords: pyzmq zeromq zmq ØMQ networking distributed socket client               server p2p publish subscribe request reply push pull               communication internet backend microservices
Platform: UNKNOWN
Classifier: Development Status :: 5 - Production/Stable
Classifier: Intended Audience :: Developers
Classifier: Programming Language :: Python :: 2
Classifier: Programming Language :: Python :: 3
Classifier: Topic :: System :: Networking
Classifier: Topic :: Communications
Classifier: Topic :: Internet
Classifier: Operating System :: MacOS :: MacOS X
Classifier: Operating System :: Microsoft :: Windows
Classifier: Operating System :: POSIX
Classifier: License :: OSI Approved :: GNU Lesser General Public License v2 or later (LGPLv2+)
